mscv/__init__.py
mscv/aug_test.py
mscv/checkpoints.py
mscv/decorators.py
mscv/meters.py
mscv/print_model.py
mscv/summary.py
mscv/version.py
mscv/cnn/__init__.py
mscv/cnn/weight_init.py
mscv/image/__init__.py
mscv/image/image_io.py
mscv-0.0.4.dist-info/LICENSE
mscv-0.0.4.dist-info/METADATA
mscv-0.0.4.dist-info/WHEEL
mscv-0.0.4.dist-info/top_level.txt
mscv-0.0.4.dist-info/RECORD
