Metadata-Version: 2.1
Name: mscv
Version: 0.0.4
Summary: mscv - A foundational python library for computer vision research.
Home-page: https://github.com/misads/mscv
Author: Haoyu Xu
Author-email: xuhaoyu@tju.edu.cn
License: MIT
Platform: UNKNOWN
Classifier: Development Status :: 3 - Alpha
Classifier: Programming Language :: Python :: 3
Classifier: License :: OSI Approved :: MIT License
Classifier: Operating System :: OS Independent
Requires-Python: >=3.6
Requires-Dist: numpy
Requires-Dist: utils-misc (>=0.0.5)
